Classfile /Users/tuuli/school/thesis_examples/ex1_factorial/temp$_39916801/Factorial.class
  Last modified Feb 17, 2016; size 769 bytes
  MD5 checksum 9353a20eb77c5294ddcc66e70898ad92
  Compiled from "Factorial.scala"
public final class Factorial
  minor version: 0
  major version: 50
  flags: ACC_PUBLIC, ACC_FINAL, ACC_SUPER
Constant pool:
   #1 = Utf8               Factorial
   #2 = Class              #1             // Factorial
   #3 = Utf8               java/lang/Object
   #4 = Class              #3             // java/lang/Object
   #5 = Utf8               Factorial.scala
   #6 = Utf8               Lscala/reflect/ScalaSignature;
   #7 = Utf8               bytes
   #8 = Utf8               e:Q!\t\tBR1di>.7\r\tqP3naRLhh9Q\"!A7\r^8sSd7CA!\tYa\"D\ri!B:dC2BA\r\te.*fM\")cC%1A(8jiz\"!)!\t!F[Lg3A1bF11A!8ji\")!da7!M]4t!\rYADH;1Q!:sCf\"a-BA\r&/3fM&1\n'RN\4b\"\t94bGR$\"%\ndB0\tYc&D-\tiC!=e>|GOP%Da7.Y4f\t4GCSLea1AQ!NAY\nA\t]J!%sG
   #9 = Utf8               fact
  #10 = Utf8               (I)Lscala/math/BigInt;
  #11 = Utf8               Factorial$
  #12 = Class              #11            // Factorial$
  #13 = Utf8               MODULE$
  #14 = Utf8               LFactorial$;
  #15 = NameAndType        #13:#14        // MODULE$:LFactorial$;
  #16 = Fieldref           #12.#15        // Factorial$.MODULE$:LFactorial$;
  #17 = NameAndType        #9:#10         // fact:(I)Lscala/math/BigInt;
  #18 = Methodref          #12.#17        // Factorial$.fact:(I)Lscala/math/BigInt;
  #19 = Utf8               main
  #20 = Utf8               ([Ljava/lang/String;)V
  #21 = NameAndType        #19:#20        // main:([Ljava/lang/String;)V
  #22 = Methodref          #12.#21        // Factorial$.main:([Ljava/lang/String;)V
  #23 = Utf8               Code
  #24 = Utf8               SourceFile
  #25 = Utf8               RuntimeVisibleAnnotations
  #26 = Utf8               ScalaSig
{
  public static scala.math.BigInt fact(int);
    descriptor: (I)Lscala/math/BigInt;
    flags: ACC_PUBLIC, ACC_STATIC
    Code:
      stack=2, locals=1, args_size=1
         0: getstatic     #16                 // Field Factorial$.MODULE$:LFactorial$;
         3: iload_0
         4: invokevirtual #18                 // Method Factorial$.fact:(I)Lscala/math/BigInt;
         7: areturn

  public static void main(java.lang.String[]);
    descriptor: ([Ljava/lang/String;)V
    flags: ACC_PUBLIC, ACC_STATIC
    Code:
      stack=2, locals=1, args_size=1
         0: getstatic     #16                 // Field Factorial$.MODULE$:LFactorial$;
         3: aload_0
         4: invokevirtual #22                 // Method Factorial$.main:([Ljava/lang/String;)V
         7: return
}
SourceFile: "Factorial.scala"
RuntimeVisibleAnnotations:
  0: #6(#7=s#8)
Error: unknown attribute
  ScalaSig: length = 0x3
   05 00 00
