Classfile /Users/tuuli/school/thesis_examples/ex4_shared_closure/temp$_39916801/CounterKt.class
  Last modified Mar 1, 2016; size 2705 bytes
  MD5 checksum 22669d3c6ead977dd0d126fcae146d33
  Compiled from "Counter.kt"
public final class CounterKt
  minor version: 0
  major version: 50
  flags: ACC_PUBLIC, ACC_FINAL, ACC_SUPER
Constant pool:
    #1 = Utf8               CounterKt
    #2 = Class              #1            // CounterKt
    #3 = Utf8               java/lang/Object
    #4 = Class              #3            // java/lang/Object
    #5 = Utf8               incrementCounter
    #6 = Utf8               Lkotlin/jvm/functions/Function0;
    #7 = Utf8               Lkotlin/jvm/functions/Function0<Lkotlin/Unit;>;
    #8 = Utf8               Lorg/jetbrains/annotations/Nullable;
    #9 = Utf8               getIncrementCounter
   #10 = Utf8               ()Lkotlin/jvm/functions/Function0;
   #11 = NameAndType        #5:#6         // incrementCounter:Lkotlin/jvm/functions/Function0;
   #12 = Fieldref           #2.#11        // CounterKt.incrementCounter:Lkotlin/jvm/functions/Function0;
   #13 = Utf8               setIncrementCounter
   #14 = Utf8               (Lkotlin/jvm/functions/Function0;)V
   #15 = Utf8               <set-?>
   #16 = Utf8               getCounter
   #17 = Utf8               Lkotlin/jvm/functions/Function0<Ljava/lang/Integer;>;
   #18 = Utf8               getGetCounter
   #19 = NameAndType        #16:#6        // getCounter:Lkotlin/jvm/functions/Function0;
   #20 = Fieldref           #2.#19        // CounterKt.getCounter:Lkotlin/jvm/functions/Function0;
   #21 = Utf8               setGetCounter
   #22 = Utf8               initCounter
   #23 = Utf8               ()V
   #24 = Utf8               kotlin/jvm/internal/Ref$IntRef
   #25 = Class              #24           // kotlin/jvm/internal/Ref$IntRef
   #26 = Utf8               <init>
   #27 = NameAndType        #26:#23       // "<init>":()V
   #28 = Methodref          #25.#27       // kotlin/jvm/internal/Ref$IntRef."<init>":()V
   #29 = Utf8               element
   #30 = Utf8               I
   #31 = NameAndType        #29:#30       // element:I
   #32 = Fieldref           #25.#31       // kotlin/jvm/internal/Ref$IntRef.element:I
   #33 = Utf8               CounterKt$initCounter$1
   #34 = Class              #33           // CounterKt$initCounter$1
   #35 = Utf8               (Lkotlin/jvm/internal/Ref$IntRef;)V
   #36 = NameAndType        #26:#35       // "<init>":(Lkotlin/jvm/internal/Ref$IntRef;)V
   #37 = Methodref          #34.#36       // CounterKt$initCounter$1."<init>":(Lkotlin/jvm/internal/Ref$IntRef;)V
   #38 = Utf8               kotlin/jvm/functions/Function0
   #39 = Class              #38           // kotlin/jvm/functions/Function0
   #40 = Utf8               CounterKt$initCounter$2
   #41 = Class              #40           // CounterKt$initCounter$2
   #42 = Methodref          #41.#36       // CounterKt$initCounter$2."<init>":(Lkotlin/jvm/internal/Ref$IntRef;)V
   #43 = Utf8               c
   #44 = Utf8               Lkotlin/jvm/internal/Ref$IntRef;
   #45 = Utf8               main
   #46 = Utf8               ([Ljava/lang/String;)V
   #47 = Utf8               Lorg/jetbrains/annotations/NotNull;
   #48 = Utf8               args
   #49 = String             #48           // args
   #50 = Utf8               kotlin/jvm/internal/Intrinsics
   #51 = Class              #50           // kotlin/jvm/internal/Intrinsics
   #52 = Utf8               checkParameterIsNotNull
   #53 = Utf8               (Ljava/lang/Object;Ljava/lang/String;)V
   #54 = NameAndType        #52:#53       // checkParameterIsNotNull:(Ljava/lang/Object;Ljava/lang/String;)V
   #55 = Methodref          #51.#54       // kotlin/jvm/internal/Intrinsics.checkParameterIsNotNull:(Ljava/lang/Object;Ljava/lang/String;)V
   #56 = NameAndType        #22:#23       // initCounter:()V
   #57 = Methodref          #2.#56        // CounterKt.initCounter:()V
   #58 = Utf8               throwNpe
   #59 = NameAndType        #58:#23       // throwNpe:()V
   #60 = Methodref          #51.#59       // kotlin/jvm/internal/Intrinsics.throwNpe:()V
   #61 = Utf8               invoke
   #62 = Utf8               ()Ljava/lang/Object;
   #63 = NameAndType        #61:#62       // invoke:()Ljava/lang/Object;
   #64 = InterfaceMethodref #39.#63       // kotlin/jvm/functions/Function0.invoke:()Ljava/lang/Object;
   #65 = Utf8               java/lang/Number
   #66 = Class              #65           // java/lang/Number
   #67 = Utf8               intValue
   #68 = Utf8               ()I
   #69 = NameAndType        #67:#68       // intValue:()I
   #70 = Methodref          #66.#69       // java/lang/Number.intValue:()I
   #71 = Utf8               kotlin/io/ConsoleKt
   #72 = Class              #71           // kotlin/io/ConsoleKt
   #73 = Utf8               println
   #74 = Utf8               (I)V
   #75 = NameAndType        #73:#74       // println:(I)V
   #76 = Methodref          #72.#75       // kotlin/io/ConsoleKt.println:(I)V
   #77 = Utf8               [Ljava/lang/String;
   #78 = Utf8               Lkotlin/jvm/internal/KotlinFileFacade;
   #79 = Utf8               version
   #80 = Integer            1
   #81 = Integer            0
   #82 = Utf8               abiVersion
   #83 = Integer            32
   #84 = Utf8               data
   #85 = Utf8               !Q!AA!B\t\"A\t)#!9QAGi'Uia#a%DI!!Ca=kA\tQ9!%\nrA!D\n%\t$G1\t6aB\t!b+EBa\t\t5)BA1a\t'R)!!CC\r!6q
   #86 = Utf8               strings
   #87 = Utf8               Lkotlin/Function0;
   #88 = Utf8
   #89 = Utf8               Counter.kt
   #90 = Utf8               Signature
   #91 = Utf8               RuntimeInvisibleAnnotations
   #92 = Utf8               Code
   #93 = Utf8               LineNumberTable
   #94 = Utf8               ()Lkotlin/jvm/functions/Function0<Lkotlin/Unit;>;
   #95 = Utf8               LocalVariableTable
   #96 = Utf8               (Lkotlin/jvm/functions/Function0<Lkotlin/Unit;>;)V
   #97 = Utf8               RuntimeInvisibleParameterAnnotations
   #98 = Utf8               ()Lkotlin/jvm/functions/Function0<Ljava/lang/Integer;>;
   #99 = Utf8               (Lkotlin/jvm/functions/Function0<Ljava/lang/Integer;>;)V
  #100 = Utf8               StackMapTable
  #101 = Utf8               SourceFile
  #102 = Utf8               InnerClasses
  #103 = Utf8               RuntimeVisibleAnnotations
{
  private static kotlin.jvm.functions.Function0<kotlin.Unit> incrementCounter;
    descriptor: Lkotlin/jvm/functions/Function0;
    flags: ACC_PRIVATE, ACC_STATIC
    Signature: #7                           // Lkotlin/jvm/functions/Function0<Lkotlin/Unit;>;
    RuntimeInvisibleAnnotations:
      0: #8()

  private static kotlin.jvm.functions.Function0<java.lang.Integer> getCounter;
    descriptor: Lkotlin/jvm/functions/Function0;
    flags: ACC_PRIVATE, ACC_STATIC
    Signature: #17                          // Lkotlin/jvm/functions/Function0<Ljava/lang/Integer;>;
    RuntimeInvisibleAnnotations:
      0: #8()

  public static final kotlin.jvm.functions.Function0<kotlin.Unit> getIncrementCounter();
    descriptor: ()Lkotlin/jvm/functions/Function0;
    flags: ACC_PUBLIC, ACC_STATIC, ACC_FINAL
    Code:
      stack=1, locals=0, args_size=0
         0: getstatic     #12                 // Field incrementCounter:Lkotlin/jvm/functions/Function0;
         3: areturn
      LineNumberTable:
        line 1: 0
    Signature: #94                          // ()Lkotlin/jvm/functions/Function0<Lkotlin/Unit;>;
    RuntimeInvisibleAnnotations:
      0: #8()

  public static final void setIncrementCounter(kotlin.jvm.functions.Function0<kotlin.Unit>);
    descriptor: (Lkotlin/jvm/functions/Function0;)V
    flags: ACC_PUBLIC, ACC_STATIC, ACC_FINAL
    Code:
      stack=1, locals=1, args_size=1
         0: aload_0
         1: putstatic     #12                 // Field incrementCounter:Lkotlin/jvm/functions/Function0;
         4: return
      LocalVariableTable:
        Start  Length  Slot  Name   Signature
            0       5     0 <set-?>   Lkotlin/jvm/functions/Function0;
      LineNumberTable:
        line 1: 0
    Signature: #96                          // (Lkotlin/jvm/functions/Function0<Lkotlin/Unit;>;)V
    RuntimeInvisibleParameterAnnotations:
      0:
        0: #8()

  public static final kotlin.jvm.functions.Function0<java.lang.Integer> getGetCounter();
    descriptor: ()Lkotlin/jvm/functions/Function0;
    flags: ACC_PUBLIC, ACC_STATIC, ACC_FINAL
    Code:
      stack=1, locals=0, args_size=0
         0: getstatic     #20                 // Field getCounter:Lkotlin/jvm/functions/Function0;
         3: areturn
      LineNumberTable:
        line 2: 0
    Signature: #98                          // ()Lkotlin/jvm/functions/Function0<Ljava/lang/Integer;>;
    RuntimeInvisibleAnnotations:
      0: #8()

  public static final void setGetCounter(kotlin.jvm.functions.Function0<java.lang.Integer>);
    descriptor: (Lkotlin/jvm/functions/Function0;)V
    flags: ACC_PUBLIC, ACC_STATIC, ACC_FINAL
    Code:
      stack=1, locals=1, args_size=1
         0: aload_0
         1: putstatic     #20                 // Field getCounter:Lkotlin/jvm/functions/Function0;
         4: return
      LocalVariableTable:
        Start  Length  Slot  Name   Signature
            0       5     0 <set-?>   Lkotlin/jvm/functions/Function0;
      LineNumberTable:
        line 2: 0
    Signature: #99                          // (Lkotlin/jvm/functions/Function0<Ljava/lang/Integer;>;)V
    RuntimeInvisibleParameterAnnotations:
      0:
        0: #8()

  public static final void initCounter();
    descriptor: ()V
    flags: ACC_PUBLIC, ACC_STATIC, ACC_FINAL
    Code:
      stack=3, locals=1, args_size=0
         0: new           #25                 // class kotlin/jvm/internal/Ref$IntRef
         3: dup
         4: invokespecial #28                 // Method kotlin/jvm/internal/Ref$IntRef."<init>":()V
         7: astore_0
         8: aload_0
         9: iconst_0
        10: putfield      #32                 // Field kotlin/jvm/internal/Ref$IntRef.element:I
        13: new           #34                 // class CounterKt$initCounter$1
        16: dup
        17: aload_0
        18: invokespecial #37                 // Method CounterKt$initCounter$1."<init>":(Lkotlin/jvm/internal/Ref$IntRef;)V
        21: checkcast     #39                 // class kotlin/jvm/functions/Function0
        24: putstatic     #12                 // Field incrementCounter:Lkotlin/jvm/functions/Function0;
        27: new           #41                 // class CounterKt$initCounter$2
        30: dup
        31: aload_0
        32: invokespecial #42                 // Method CounterKt$initCounter$2."<init>":(Lkotlin/jvm/internal/Ref$IntRef;)V
        35: checkcast     #39                 // class kotlin/jvm/functions/Function0
        38: putstatic     #20                 // Field getCounter:Lkotlin/jvm/functions/Function0;
        41: aconst_null
        42: astore_0
        43: return
      LocalVariableTable:
        Start  Length  Slot  Name   Signature
           13      31     0     c   Lkotlin/jvm/internal/Ref$IntRef;
      LineNumberTable:
        line 5: 0
        line 6: 13
        line 7: 27
        line 8: 43

  public static final void main(java.lang.String[]);
    descriptor: ([Ljava/lang/String;)V
    flags: ACC_PUBLIC, ACC_STATIC, ACC_FINAL
    Code:
      stack=2, locals=1, args_size=1
         0: aload_0
         1: ldc           #49                 // String args
         3: invokestatic  #55                 // Method kotlin/jvm/internal/Intrinsics.checkParameterIsNotNull:(Ljava/lang/Object;Ljava/lang/String;)V
         6: invokestatic  #57                 // Method initCounter:()V
         9: getstatic     #20                 // Field getCounter:Lkotlin/jvm/functions/Function0;
        12: dup
        13: ifnonnull     19
        16: invokestatic  #60                 // Method kotlin/jvm/internal/Intrinsics.throwNpe:()V
        19: invokeinterface #64,  1           // InterfaceMethod kotlin/jvm/functions/Function0.invoke:()Ljava/lang/Object;
        24: checkcast     #66                 // class java/lang/Number
        27: invokevirtual #70                 // Method java/lang/Number.intValue:()I
        30: invokestatic  #76                 // Method kotlin/io/ConsoleKt.println:(I)V
        33: getstatic     #12                 // Field incrementCounter:Lkotlin/jvm/functions/Function0;
        36: dup
        37: ifnonnull     43
        40: invokestatic  #60                 // Method kotlin/jvm/internal/Intrinsics.throwNpe:()V
        43: invokeinterface #64,  1           // InterfaceMethod kotlin/jvm/functions/Function0.invoke:()Ljava/lang/Object;
        48: pop
        49: getstatic     #20                 // Field getCounter:Lkotlin/jvm/functions/Function0;
        52: dup
        53: ifnonnull     59
        56: invokestatic  #60                 // Method kotlin/jvm/internal/Intrinsics.throwNpe:()V
        59: invokeinterface #64,  1           // InterfaceMethod kotlin/jvm/functions/Function0.invoke:()Ljava/lang/Object;
        64: checkcast     #66                 // class java/lang/Number
        67: invokevirtual #70                 // Method java/lang/Number.intValue:()I
        70: invokestatic  #76                 // Method kotlin/io/ConsoleKt.println:(I)V
        73: getstatic     #12                 // Field incrementCounter:Lkotlin/jvm/functions/Function0;
        76: dup
        77: ifnonnull     83
        80: invokestatic  #60                 // Method kotlin/jvm/internal/Intrinsics.throwNpe:()V
        83: invokeinterface #64,  1           // InterfaceMethod kotlin/jvm/functions/Function0.invoke:()Ljava/lang/Object;
        88: pop
        89: getstatic     #12                 // Field incrementCounter:Lkotlin/jvm/functions/Function0;
        92: dup
        93: ifnonnull     99
        96: invokestatic  #60                 // Method kotlin/jvm/internal/Intrinsics.throwNpe:()V
        99: invokeinterface #64,  1           // InterfaceMethod kotlin/jvm/functions/Function0.invoke:()Ljava/lang/Object;
       104: pop
       105: getstatic     #20                 // Field getCounter:Lkotlin/jvm/functions/Function0;
       108: dup
       109: ifnonnull     115
       112: invokestatic  #60                 // Method kotlin/jvm/internal/Intrinsics.throwNpe:()V
       115: invokeinterface #64,  1           // InterfaceMethod kotlin/jvm/functions/Function0.invoke:()Ljava/lang/Object;
       120: checkcast     #66                 // class java/lang/Number
       123: invokevirtual #70                 // Method java/lang/Number.intValue:()I
       126: invokestatic  #76                 // Method kotlin/io/ConsoleKt.println:(I)V
       129: return
      LocalVariableTable:
        Start  Length  Slot  Name   Signature
            0     130     0  args   [Ljava/lang/String;
      LineNumberTable:
        line 11: 6
        line 12: 9
        line 13: 33
        line 14: 49
        line 15: 73
        line 16: 89
        line 17: 105
        line 18: 129
      StackMapTable: number_of_entries = 6
        frame_type = 83 /* same_locals_1_stack_item */
          stack = [ class kotlin/jvm/functions/Function0 ]
        frame_type = 87 /* same_locals_1_stack_item */
          stack = [ class kotlin/jvm/functions/Function0 ]
        frame_type = 79 /* same_locals_1_stack_item */
          stack = [ class kotlin/jvm/functions/Function0 ]
        frame_type = 87 /* same_locals_1_stack_item */
          stack = [ class kotlin/jvm/functions/Function0 ]
        frame_type = 79 /* same_locals_1_stack_item */
          stack = [ class kotlin/jvm/functions/Function0 ]
        frame_type = 79 /* same_locals_1_stack_item */
          stack = [ class kotlin/jvm/functions/Function0 ]
    RuntimeInvisibleParameterAnnotations:
      0:
        0: #47()
}
SourceFile: "Counter.kt"
InnerClasses:
     public static final #34; //class CounterKt$initCounter$1
     public static final #41; //class CounterKt$initCounter$2
RuntimeVisibleAnnotations:
  0: #78(#79=[I#80,I#81,I#80],#82=I#83,#84=[s#85],#86=[s#16,s#87,s#88,s#18,s#10,s#21,s#14,s#1,s#5,s#88,s#9,s#13,s#22,s#45,s#48,s#88,s#88,s#46])
