Classfile /Users/tuuli/school/thesis_examples/ex2_closure/temp$_39916801/SimpleClosureKt.class
  Last modified Feb 18, 2016; size 1568 bytes
  MD5 checksum 9f476885465e491984829275f006c9cc
  Compiled from "SimpleClosure.kt"
public final class SimpleClosureKt
  minor version: 0
  major version: 50
  flags: ACC_PUBLIC, ACC_FINAL, ACC_SUPER
Constant pool:
   #1 = Utf8               SimpleClosureKt
   #2 = Class              #1             // SimpleClosureKt
   #3 = Utf8               java/lang/Object
   #4 = Class              #3             // java/lang/Object
   #5 = Utf8               add
   #6 = Utf8               (I)Lkotlin/jvm/functions/Function1;
   #7 = Utf8               Lorg/jetbrains/annotations/NotNull;
   #8 = Utf8               SimpleClosureKt$add$1
   #9 = Class              #8             // SimpleClosureKt$add$1
  #10 = Utf8               <init>
  #11 = Utf8               (I)V
  #12 = NameAndType        #10:#11        // "<init>":(I)V
  #13 = Methodref          #9.#12         // SimpleClosureKt$add$1."<init>":(I)V
  #14 = Utf8               kotlin/jvm/functions/Function1
  #15 = Class              #14            // kotlin/jvm/functions/Function1
  #16 = Utf8               x
  #17 = Utf8               I
  #18 = Utf8               main
  #19 = Utf8               ([Ljava/lang/String;)V
  #20 = Utf8               args
  #21 = String             #20            // args
  #22 = Utf8               kotlin/jvm/internal/Intrinsics
  #23 = Class              #22            // kotlin/jvm/internal/Intrinsics
  #24 = Utf8               checkParameterIsNotNull
  #25 = Utf8               (Ljava/lang/Object;Ljava/lang/String;)V
  #26 = NameAndType        #24:#25        // checkParameterIsNotNull:(Ljava/lang/Object;Ljava/lang/String;)V
  #27 = Methodref          #23.#26        // kotlin/jvm/internal/Intrinsics.checkParameterIsNotNull:(Ljava/lang/Object;Ljava/lang/String;)V
  #28 = NameAndType        #5:#6          // add:(I)Lkotlin/jvm/functions/Function1;
  #29 = Methodref          #2.#28         // SimpleClosureKt.add:(I)Lkotlin/jvm/functions/Function1;
  #30 = Utf8               java/lang/Integer
  #31 = Class              #30            // java/lang/Integer
  #32 = Utf8               valueOf
  #33 = Utf8               (I)Ljava/lang/Integer;
  #34 = NameAndType        #32:#33        // valueOf:(I)Ljava/lang/Integer;
  #35 = Methodref          #31.#34        // java/lang/Integer.valueOf:(I)Ljava/lang/Integer;
  #36 = Utf8               invoke
  #37 = Utf8               (Ljava/lang/Object;)Ljava/lang/Object;
  #38 = NameAndType        #36:#37        // invoke:(Ljava/lang/Object;)Ljava/lang/Object;
  #39 = InterfaceMethodref #15.#38        // kotlin/jvm/functions/Function1.invoke:(Ljava/lang/Object;)Ljava/lang/Object;
  #40 = Utf8               java/lang/Number
  #41 = Class              #40            // java/lang/Number
  #42 = Utf8               intValue
  #43 = Utf8               ()I
  #44 = NameAndType        #42:#43        // intValue:()I
  #45 = Methodref          #41.#44        // java/lang/Number.intValue:()I
  #46 = Utf8               kotlin/io/ConsoleKt
  #47 = Class              #46            // kotlin/io/ConsoleKt
  #48 = Utf8               println
  #49 = NameAndType        #48:#11        // println:(I)V
  #50 = Methodref          #47.#49        // kotlin/io/ConsoleKt.println:(I)V
  #51 = Utf8               add10
  #52 = Utf8               Lkotlin/jvm/functions/Function1;
  #53 = Utf8               [Ljava/lang/String;
  #54 = Utf8               Lkotlin/jvm/internal/KotlinFileFacade;
  #55 = Utf8               version
  #56 = Integer            1
  #57 = Integer            0
  #58 = Utf8               abiVersion
  #59 = Integer            32
  #60 = Utf8               data
  #61 = Utf8               Q!AA!B\t\"AA\t\"B\tQRI!!C%\"\r1I2ca\tAk!Q\"\r3A9!\n%\t\r#\t\"+
  #62 = Utf8               strings
  #63 = Utf8               Lkotlin/Function1;
  #64 = Utf8
  #65 = Utf8               SimpleClosure.kt
  #66 = Utf8               Code
  #67 = Utf8               LocalVariableTable
  #68 = Utf8               LineNumberTable
  #69 = Utf8               Signature
  #70 = Utf8               (I)Lkotlin/jvm/functions/Function1<Ljava/lang/Integer;Ljava/lang/Integer;>;
  #71 = Utf8               RuntimeInvisibleAnnotations
  #72 = Utf8               RuntimeInvisibleParameterAnnotations
  #73 = Utf8               SourceFile
  #74 = Utf8               InnerClasses
  #75 = Utf8               RuntimeVisibleAnnotations
{
  public static final kotlin.jvm.functions.Function1<java.lang.Integer, java.lang.Integer> add(int);
    descriptor: (I)Lkotlin/jvm/functions/Function1;
    flags: ACC_PUBLIC, ACC_STATIC, ACC_FINAL
    Code:
      stack=3, locals=1, args_size=1
         0: new           #9                  // class SimpleClosureKt$add$1
         3: dup
         4: iload_0
         5: invokespecial #13                 // Method SimpleClosureKt$add$1."<init>":(I)V
         8: checkcast     #15                 // class kotlin/jvm/functions/Function1
        11: areturn
      LocalVariableTable:
        Start  Length  Slot  Name   Signature
            0      12     0     x   I
      LineNumberTable:
        line 2: 0
    Signature: #70                          // (I)Lkotlin/jvm/functions/Function1<Ljava/lang/Integer;Ljava/lang/Integer;>;
    RuntimeInvisibleAnnotations:
      0: #7()

  public static final void main(java.lang.String[]);
    descriptor: ([Ljava/lang/String;)V
    flags: ACC_PUBLIC, ACC_STATIC, ACC_FINAL
    Code:
      stack=2, locals=2, args_size=1
         0: aload_0
         1: ldc           #21                 // String args
         3: invokestatic  #27                 // Method kotlin/jvm/internal/Intrinsics.checkParameterIsNotNull:(Ljava/lang/Object;Ljava/lang/String;)V
         6: iconst_5
         7: invokestatic  #29                 // Method add:(I)Lkotlin/jvm/functions/Function1;
        10: iconst_4
        11: invokestatic  #35                 // Method java/lang/Integer.valueOf:(I)Ljava/lang/Integer;
        14: invokeinterface #39,  2           // InterfaceMethod kotlin/jvm/functions/Function1.invoke:(Ljava/lang/Object;)Ljava/lang/Object;
        19: checkcast     #41                 // class java/lang/Number
        22: invokevirtual #45                 // Method java/lang/Number.intValue:()I
        25: invokestatic  #50                 // Method kotlin/io/ConsoleKt.println:(I)V
        28: bipush        10
        30: invokestatic  #29                 // Method add:(I)Lkotlin/jvm/functions/Function1;
        33: astore_1
        34: aload_1
        35: bipush        90
        37: invokestatic  #35                 // Method java/lang/Integer.valueOf:(I)Ljava/lang/Integer;
        40: invokeinterface #39,  2           // InterfaceMethod kotlin/jvm/functions/Function1.invoke:(Ljava/lang/Object;)Ljava/lang/Object;
        45: checkcast     #41                 // class java/lang/Number
        48: invokevirtual #45                 // Method java/lang/Number.intValue:()I
        51: invokestatic  #50                 // Method kotlin/io/ConsoleKt.println:(I)V
        54: aload_1
        55: sipush        999
        58: invokestatic  #35                 // Method java/lang/Integer.valueOf:(I)Ljava/lang/Integer;
        61: invokeinterface #39,  2           // InterfaceMethod kotlin/jvm/functions/Function1.invoke:(Ljava/lang/Object;)Ljava/lang/Object;
        66: checkcast     #41                 // class java/lang/Number
        69: invokevirtual #45                 // Method java/lang/Number.intValue:()I
        72: invokestatic  #50                 // Method kotlin/io/ConsoleKt.println:(I)V
        75: return
      LocalVariableTable:
        Start  Length  Slot  Name   Signature
           34      42     1 add10   Lkotlin/jvm/functions/Function1;
            0      76     0  args   [Ljava/lang/String;
      LineNumberTable:
        line 6: 6
        line 8: 28
        line 10: 34
        line 11: 54
        line 12: 75
    RuntimeInvisibleParameterAnnotations:
      0:
        0: #7()
}
SourceFile: "SimpleClosure.kt"
InnerClasses:
     public static final #9; //class SimpleClosureKt$add$1
RuntimeVisibleAnnotations:
  0: #54(#55=[I#56,I#57,I#56],#58=I#59,#60=[s#61],#62=[s#5,s#63,s#64,s#16,s#1,s#18,s#64,s#20,s#64,s#64,s#19])
