Classfile /Users/tuuli/school/thesis_examples/ex2_closure/temp$_39916801/SimpleClosureKt$add$1.class
  Last modified Feb 18, 2016; size 1187 bytes
  MD5 checksum f003a1100b0effe7cab2fdf626997e49
  Compiled from "SimpleClosure.kt"
final class SimpleClosureKt$add$1 extends kotlin.jvm.internal.Lambda implements kotlin.jvm.functions.Function1<java.lang.Integer, java.lang.Integer>
  minor version: 0
  major version: 50
  flags: ACC_FINAL, ACC_SUPER
Constant pool:
   #1 = Utf8               SimpleClosureKt$add$1
   #2 = Class              #1             // SimpleClosureKt$add$1
   #3 = Utf8               Lkotlin/jvm/internal/Lambda;Lkotlin/jvm/functions/Function1<Ljava/lang/Integer;Ljava/lang/Integer;>;
   #4 = Utf8               kotlin/jvm/internal/Lambda
   #5 = Class              #4             // kotlin/jvm/internal/Lambda
   #6 = Utf8               kotlin/jvm/functions/Function1
   #7 = Class              #6             // kotlin/jvm/functions/Function1
   #8 = Utf8               invoke
   #9 = Utf8               (Ljava/lang/Object;)Ljava/lang/Object;
  #10 = Utf8               java/lang/Number
  #11 = Class              #10            // java/lang/Number
  #12 = Utf8               intValue
  #13 = Utf8               ()I
  #14 = NameAndType        #12:#13        // intValue:()I
  #15 = Methodref          #11.#14        // java/lang/Number.intValue:()I
  #16 = Utf8               (I)I
  #17 = NameAndType        #8:#16         // invoke:(I)I
  #18 = Methodref          #2.#17         // SimpleClosureKt$add$1.invoke:(I)I
  #19 = Utf8               java/lang/Integer
  #20 = Class              #19            // java/lang/Integer
  #21 = Utf8               valueOf
  #22 = Utf8               (I)Ljava/lang/Integer;
  #23 = NameAndType        #21:#22        // valueOf:(I)Ljava/lang/Integer;
  #24 = Methodref          #20.#23        // java/lang/Integer.valueOf:(I)Ljava/lang/Integer;
  #25 = Utf8               $x
  #26 = Utf8               I
  #27 = NameAndType        #25:#26        // $x:I
  #28 = Fieldref           #2.#27         // SimpleClosureKt$add$1.$x:I
  #29 = Utf8               this
  #30 = Utf8               LSimpleClosureKt$add$1;
  #31 = Utf8               y
  #32 = Utf8               <init>
  #33 = Utf8               (I)V
  #34 = NameAndType        #32:#33        // "<init>":(I)V
  #35 = Methodref          #5.#34         // kotlin/jvm/internal/Lambda."<init>":(I)V
  #36 = Utf8               Lkotlin/jvm/internal/KotlinSyntheticClass;
  #37 = Utf8               version
  #38 = Integer            1
  #39 = Integer            0
  #40 = Utf8               abiVersion
  #41 = Integer            32
  #42 = Utf8               Lkotlin/jvm/internal/KotlinFunction;
  #43 = Utf8               data
  #44 = Utf8               Q!!B\t5\tA\ri'R!
  #45 = Utf8               strings
  #46 = Utf8               <anonymous>
  #47 = Utf8
  #48 = Utf8               SimpleClosureKt
  #49 = Class              #48            // SimpleClosureKt
  #50 = Utf8               add
  #51 = Utf8               (I)Lkotlin/jvm/functions/Function1;
  #52 = NameAndType        #50:#51        // add:(I)Lkotlin/jvm/functions/Function1;
  #53 = Utf8               SimpleClosure.kt
  #54 = Utf8               Code
  #55 = Utf8               LocalVariableTable
  #56 = Utf8               LineNumberTable
  #57 = Utf8               Signature
  #58 = Utf8               SourceFile
  #59 = Utf8               EnclosingMethod
  #60 = Utf8               InnerClasses
  #61 = Utf8               RuntimeVisibleAnnotations
{
  final int $x;
    descriptor: I
    flags: ACC_FINAL, ACC_SYNTHETIC

  public java.lang.Object invoke(java.lang.Object);
    descriptor: (Ljava/lang/Object;)Ljava/lang/Object;
    flags: ACC_PUBLIC, ACC_BRIDGE, ACC_SYNTHETIC
    Code:
      stack=2, locals=2, args_size=2
         0: aload_0
         1: aload_1
         2: checkcast     #11                 // class java/lang/Number
         5: invokevirtual #15                 // Method java/lang/Number.intValue:()I
         8: invokevirtual #18                 // Method invoke:(I)I
        11: invokestatic  #24                 // Method java/lang/Integer.valueOf:(I)Ljava/lang/Integer;
        14: areturn

  public final int invoke(int);
    descriptor: (I)I
    flags: ACC_PUBLIC, ACC_FINAL
    Code:
      stack=2, locals=2, args_size=2
         0: aload_0
         1: getfield      #28                 // Field $x:I
         4: iload_1
         5: iadd
         6: ireturn
      LocalVariableTable:
        Start  Length  Slot  Name   Signature
            0       7     0  this   LSimpleClosureKt$add$1;
            0       7     1     y   I
      LineNumberTable:
        line 2: 0

  SimpleClosureKt$add$1(int);
    descriptor: (I)V
    flags:
    Code:
      stack=2, locals=2, args_size=2
         0: aload_0
         1: iload_1
         2: putfield      #28                 // Field $x:I
         5: aload_0
         6: iconst_1
         7: invokespecial #35                 // Method kotlin/jvm/internal/Lambda."<init>":(I)V
        10: return
}
Signature: #3                           // Lkotlin/jvm/internal/Lambda;Lkotlin/jvm/functions/Function1<Ljava/lang/Integer;Ljava/lang/Integer;>;
SourceFile: "SimpleClosure.kt"
EnclosingMethod: #49.#52                // SimpleClosureKt.add
InnerClasses:
     public static final #2; //class SimpleClosureKt$add$1
RuntimeVisibleAnnotations:
  0: #36(#37=[I#38,I#39,I#38],#40=I#41)
  1: #42(#37=[I#38,I#39,I#38],#40=I#41,#43=[s#44],#45=[s#46,s#47,s#31,s#8])
