Classfile /Users/tuuli/school/thesis_examples/ex4_shared_closure/temp$_39916801/Counter.class
  Last modified Mar 1, 2016; size 1435 bytes
  MD5 checksum 098504f8b771c6f374fa77f5b369cca1
  Compiled from "Counter.scala"
public final class Counter
  minor version: 0
  major version: 50
  flags: ACC_PUBLIC, ACC_FINAL, ACC_SUPER
Constant pool:
   #1 = Utf8               Counter
   #2 = Class              #1             // Counter
   #3 = Utf8               java/lang/Object
   #4 = Class              #3             // java/lang/Object
   #5 = Utf8               Counter.scala
   #6 = Utf8               Lscala/reflect/ScalaSignature;
   #7 = Utf8               bytes
   #8 = Utf8               \t;Q!\t\tqaQ8v]R,'OCaT-9usz5\t!AB\t!BAD_VtG/:QCAa!\"AM\r\1\n=a!AB!osJ+g\rC!#=S:LGO!9Aca\n)E5oGJ,W.8u>,h^3s+1cA3%\n\rVt7\r^5p]B\"a\nma!B+oSRDq!HAa$j]X-\3oi{WO;fe~#S-3}Aq\ta#AyIEBaAI!B1!E5oGJ,W.8u>,h^3sA!9Aea\n)AC4fi{WO;feV\taE/\"a\n%b!aA%oi\"91fa\naAD4fi{WO;fe~#S-35Bq\ta0KAJO$8i\;oiC2!'nC&tGCA\r4!16\t'oZ:-1(8\t)I:bsBiJ!a\rAX\rZ3g\tidHTiJLgnw1AQQ1\"8ji{WO;feR\t
   #9 = Utf8               initCounter
  #10 = Utf8               ()V
  #11 = Utf8               Counter$
  #12 = Class              #11            // Counter$
  #13 = Utf8               MODULE$
  #14 = Utf8               LCounter$;
  #15 = NameAndType        #13:#14        // MODULE$:LCounter$;
  #16 = Fieldref           #12.#15        // Counter$.MODULE$:LCounter$;
  #17 = NameAndType        #9:#10         // initCounter:()V
  #18 = Methodref          #12.#17        // Counter$.initCounter:()V
  #19 = Utf8               main
  #20 = Utf8               ([Ljava/lang/String;)V
  #21 = NameAndType        #19:#20        // main:([Ljava/lang/String;)V
  #22 = Methodref          #12.#21        // Counter$.main:([Ljava/lang/String;)V
  #23 = Utf8               getCounter_$eq
  #24 = Utf8               (Lscala/Function0;)V
  #25 = NameAndType        #23:#24        // getCounter_$eq:(Lscala/Function0;)V
  #26 = Methodref          #12.#25        // Counter$.getCounter_$eq:(Lscala/Function0;)V
  #27 = Utf8               getCounter
  #28 = Utf8               ()Lscala/Function0;
  #29 = NameAndType        #27:#28        // getCounter:()Lscala/Function0;
  #30 = Methodref          #12.#29        // Counter$.getCounter:()Lscala/Function0;
  #31 = Utf8               incrementCounter_$eq
  #32 = NameAndType        #31:#24        // incrementCounter_$eq:(Lscala/Function0;)V
  #33 = Methodref          #12.#32        // Counter$.incrementCounter_$eq:(Lscala/Function0;)V
  #34 = Utf8               incrementCounter
  #35 = NameAndType        #34:#28        // incrementCounter:()Lscala/Function0;
  #36 = Methodref          #12.#35        // Counter$.incrementCounter:()Lscala/Function0;
  #37 = Utf8               Code
  #38 = Utf8               Signature
  #39 = Utf8               (Lscala/Function0<Ljava/lang/Object;>;)V
  #40 = Utf8               ()Lscala/Function0<Ljava/lang/Object;>;
  #41 = Utf8               (Lscala/Function0<Lscala/runtime/BoxedUnit;>;)V
  #42 = Utf8               ()Lscala/Function0<Lscala/runtime/BoxedUnit;>;
  #43 = Utf8               SourceFile
  #44 = Utf8               RuntimeVisibleAnnotations
  #45 = Utf8               ScalaSig
{
  public static void initCounter();
    descriptor: ()V
    flags: ACC_PUBLIC, ACC_STATIC
    Code:
      stack=1, locals=0, args_size=0
         0: getstatic     #16                 // Field Counter$.MODULE$:LCounter$;
         3: invokevirtual #18                 // Method Counter$.initCounter:()V
         6: return

  public static void main(java.lang.String[]);
    descriptor: ([Ljava/lang/String;)V
    flags: ACC_PUBLIC, ACC_STATIC
    Code:
      stack=2, locals=1, args_size=1
         0: getstatic     #16                 // Field Counter$.MODULE$:LCounter$;
         3: aload_0
         4: invokevirtual #22                 // Method Counter$.main:([Ljava/lang/String;)V
         7: return

  public static void getCounter_$eq(scala.Function0<java.lang.Object>);
    descriptor: (Lscala/Function0;)V
    flags: ACC_PUBLIC, ACC_STATIC
    Code:
      stack=2, locals=1, args_size=1
         0: getstatic     #16                 // Field Counter$.MODULE$:LCounter$;
         3: aload_0
         4: invokevirtual #26                 // Method Counter$.getCounter_$eq:(Lscala/Function0;)V
         7: return
    Signature: #39                          // (Lscala/Function0<Ljava/lang/Object;>;)V

  public static scala.Function0<java.lang.Object> getCounter();
    descriptor: ()Lscala/Function0;
    flags: ACC_PUBLIC, ACC_STATIC
    Code:
      stack=1, locals=0, args_size=0
         0: getstatic     #16                 // Field Counter$.MODULE$:LCounter$;
         3: invokevirtual #30                 // Method Counter$.getCounter:()Lscala/Function0;
         6: areturn
    Signature: #40                          // ()Lscala/Function0<Ljava/lang/Object;>;

  public static void incrementCounter_$eq(scala.Function0<scala.runtime.BoxedUnit>);
    descriptor: (Lscala/Function0;)V
    flags: ACC_PUBLIC, ACC_STATIC
    Code:
      stack=2, locals=1, args_size=1
         0: getstatic     #16                 // Field Counter$.MODULE$:LCounter$;
         3: aload_0
         4: invokevirtual #33                 // Method Counter$.incrementCounter_$eq:(Lscala/Function0;)V
         7: return
    Signature: #41                          // (Lscala/Function0<Lscala/runtime/BoxedUnit;>;)V

  public static scala.Function0<scala.runtime.BoxedUnit> incrementCounter();
    descriptor: ()Lscala/Function0;
    flags: ACC_PUBLIC, ACC_STATIC
    Code:
      stack=1, locals=0, args_size=0
         0: getstatic     #16                 // Field Counter$.MODULE$:LCounter$;
         3: invokevirtual #36                 // Method Counter$.incrementCounter:()Lscala/Function0;
         6: areturn
    Signature: #42                          // ()Lscala/Function0<Lscala/runtime/BoxedUnit;>;
}
SourceFile: "Counter.scala"
RuntimeVisibleAnnotations:
  0: #6(#7=s#8)
Error: unknown attribute
  ScalaSig: length = 0x3
   05 00 00
